NUAAiCal/AddToGCal.py
NUAAiCal/FindFirstDayofSemester.py
NUAAiCal/GenerateICS.py
NUAAiCal/Lesson.py
NUAAiCal/__init__.py
NUAAiCal/entry.py
NUAAiCal/main.py
NUAAiCal/settings.py
NUAAiCal/tests/__init__.py
NUAAiCal/tests/test_FFDoS.py
NUAAiCal/tests/test_GenerateICS.py
NUAAiCal/tests/test_main.py
NUAAiCal-0.5.5.dist-info/DESCRIPTION.rst
NUAAiCal-0.5.5.dist-info/METADATA
NUAAiCal-0.5.5.dist-info/RECORD
NUAAiCal-0.5.5.dist-info/WHEEL
NUAAiCal-0.5.5.dist-info/entry_points.txt
NUAAiCal-0.5.5.dist-info/metadata.json
NUAAiCal-0.5.5.dist-info/top_level.txt
